abito/__init__.py
abito/core.py
abito/lib/__init__.py
abito/lib/bootstrap.py
abito/lib/significance.py
abito/lib/utils.py
abito/lib/prepare/__init__.py
abito/lib/prepare/compress.py
abito/lib/prepare/trim.py
abito/lib/stats/__init__.py
abito/lib/stats/plain.py
abito/lib/stats/weighted.py
abito-0.1.3.dist-info/LICENSE
abito-0.1.3.dist-info/METADATA
abito-0.1.3.dist-info/WHEEL
abito-0.1.3.dist-info/top_level.txt
abito-0.1.3.dist-info/RECORD
