Metadata-Version: 2.1
Name: abito
Version: 0.1.3
Summary: Package for hypothesis testing in A/B-experiments
Home-page: https://github.com/avito-tech/abito
Author: Danila Lenkov
Author-email: dlenkoff@gmail.com
License: MIT
Platform: UNKNOWN
Classifier: Development Status :: 4 - Beta
Classifier: Intended Audience :: Science/Research
Classifier: License :: OSI Approved :: MIT License
Classifier: Operating System :: OS Independent
Classifier: Programming Language :: Python :: 3.5
Classifier: Programming Language :: Python :: 3.6
Classifier: Programming Language :: Python :: 3.7
Classifier: Topic :: Scientific/Engineering
Requires-Dist: numpy (>=1.16)
Requires-Dist: scipy
